mysql_data/__init__.py
mysql_data/download.py
mysql_data/initialize.py
mysql_data/upload.py
mysql_data-0.1.1.dist-info/METADATA
mysql_data-0.1.1.dist-info/WHEEL
mysql_data-0.1.1.dist-info/top_level.txt
mysql_data-0.1.1.dist-info/RECORD
