Metadata-Version: 2.1
Name: mysql_data
Version: 0.1.1
Requires-Dist: pandas>=2.2.3
Requires-Dist: mysql-connector-python>=9.0.0
